py3dchart/__init__.py
py3dchart/chart.py
py3dchart-0.2.2.dist-info/LICENSE
py3dchart-0.2.2.dist-info/METADATA
py3dchart-0.2.2.dist-info/WHEEL
py3dchart-0.2.2.dist-info/top_level.txt
py3dchart-0.2.2.dist-info/RECORD
