Metadata-Version: 2.1
Name: py3dchart
Version: 0.2.2
Summary: A simple tool for my classmate to finish their classwork
Home-page: https://github.com/Niggoss/Wang-Lvyuan.git
Author: Wang Lvyuan
Author-email: lvyuanw@gmail.com
License: MIT
Classifier: License :: OSI Approved :: MIT License
Classifier: Programming Language :: Python
Classifier: Programming Language :: Python :: 3
Classifier: Programming Language :: Python :: 3.6
Classifier: Programming Language :: Python :: Implementation :: CPython
Classifier: Programming Language :: Python :: Implementation :: PyPy
Requires-Python: >=3.6.0
License-File: LICENSE
